itk/itkKrcahEigenToMeasureImageFilterPython.py
itk/itkHessianGaussianImageFilterPython.py
itk/itkMultiScaleHessianEnhancementImageFilterPython.py
itk/_BoneEnhancementPython.cpython-39-aarch64-linux-gnu.so
itk/itkMaximumAbsoluteValueImageFilterPython.py
itk/BoneEnhancementPython.py
itk/itkEigenToMeasureImageFilterPython.py
itk/itkDescoteauxEigenToMeasureParameterEstimationFilterPython.py
itk/itkKrcahEigenToMeasureParameterEstimationFilterPython.py
itk/itkKrcahPreprocessingImageToImageFilterPython.py
itk/itkDescoteauxEigenToMeasureImageFilterPython.py
itk/Configuration/BoneEnhancementConfig.py
itk/Configuration/BoneEnhancement_snake_case.py
itk_boneenhancement.libs/libtbb-e046f41a.so.12.9
itk_boneenhancement-0.5.1.dist-info/RECORD
itk_boneenhancement-0.5.1.dist-info/METADATA
itk_boneenhancement-0.5.1.dist-info/WHEEL
itk_boneenhancement-0.5.1.dist-info/licenses/LICENSE
